sshuttle/__init__.py
sshuttle/__main__.py
sshuttle/assembler.py
sshuttle/client.py
sshuttle/cmdline.py
sshuttle/firewall.py
sshuttle/helpers.py
sshuttle/hostwatch.py
sshuttle/linux.py
sshuttle/namespace.py
sshuttle/options.py
sshuttle/sdnotify.py
sshuttle/server.py
sshuttle/ssh.py
sshuttle/ssnet.py
sshuttle/ssyslog.py
sshuttle/sudoers.py
sshuttle/methods/__init__.py
sshuttle/methods/ipfw.py
sshuttle/methods/nat.py
sshuttle/methods/nft.py
sshuttle/methods/pf.py
sshuttle/methods/tproxy.py
sshuttle/methods/windivert.py
sshuttle-1.3.2.dist-info/METADATA
sshuttle-1.3.2.dist-info/WHEEL
sshuttle-1.3.2.dist-info/entry_points.txt
sshuttle-1.3.2.dist-info/licenses/LICENSE
sshuttle-1.3.2.dist-info/RECORD
